README.txt
setup.py
collective/__init__.py
collective.rdfadcviewlet.egg-info/PKG-INFO
collective.rdfadcviewlet.egg-info/SOURCES.txt
collective.rdfadcviewlet.egg-info/dependency_links.txt
collective.rdfadcviewlet.egg-info/entry_points.txt
collective.rdfadcviewlet.egg-info/namespace_packages.txt
collective.rdfadcviewlet.egg-info/not-zip-safe
collective.rdfadcviewlet.egg-info/requires.txt
collective.rdfadcviewlet.egg-info/top_level.txt
collective/rdfadcviewlet/__init__.py
collective/rdfadcviewlet/configure.zcml
collective/rdfadcviewlet/dublin_core.pt
collective/rdfadcviewlet/interfaces.py
collective/rdfadcviewlet/tests.py
collective/rdfadcviewlet/viewlet.py
collective/rdfadcviewlet/profiles/default/browserlayer.xml
docs/HISTORY.txt
docs/INSTALL.txt
docs/LICENSE.GPL
docs/LICENSE.txt