Metadata-Version: 1.0
Name: collective.rdfadcviewlet
Version: 1.0
Summary: Adds a viewlet that adds on your page meta with dublin core values in rdfa format, by ecreall
Home-page: http://svn.plone.org/svn/collective/
Author: Thomas Desvenain
Author-email: thomas.desvenain@gmail.com
License: GPL
Keywords: Dublin Core,RDFa,Plone
Platform: UNKNOWN
Classifier: Framework :: Plone
Classifier: Programming Language :: Python
